rs_parsepatch-0.4.4.dist-info/METADATA
rs_parsepatch-0.4.4.dist-info/WHEEL
rs_parsepatch-0.4.4.dist-info/licenses/LICENSE-MPL-2.0
rs_parsepatch/__init__.py
rs_parsepatch/rs_parsepatch.cpython-312-darwin.so
rs_parsepatch-0.4.4.dist-info/RECORD
