Metadata-Version: 2.3
Name: rs_parsepatch
Version: 0.4.4
License-File: LICENSE-MPL-2.0
Home-Page: https://github.com/mozilla/pyo3-parsepatch
Author: calixteman <cdenizet@mozilla.com>
Author-email: calixteman <cdenizet@mozilla.com>
License: MPL-2.0
Project-URL: Source Code, https://github.com/mozilla/pyo3-parsepatch
